<?xml version="1.0" encoding="utf-8"?>
<odoo>
    <record id="pos_config_view_form_pos_guardar" model="ir.ui.view">
        <field name="name">pos.config.form.view_pos_guardar</field>
        <field name="model">pos.config</field>
        <field name="inherit_id" ref="point_of_sale.pos_config_view_form"/>
        <field name="arch" type="xml">
            <sheet position="inside">
                <h2>Guardar y Cargar</h2>
                <div class="row mt16 o_settings_container">
                    <div class="col-xs-12 col-md-6 o_setting_box">
                        <div class="o_setting_left_pane">
                            <field name="load_order_option"/>
                        </div>
                        <div class="o_setting_right_pane">
                            <label for="load_order_option" string="Opci贸n para cargar ventas"/>
                        </div>
                    </div>
                    <div class="col-xs-12 col-md-6 o_setting_box">
                        <div class="o_setting_left_pane">
                            <field name="save_order_option"/>
                        </div>
                        <div class="o_setting_right_pane">
                            <label for="save_order_option" string="Opci贸n para guardar ventas"/>
                        </div>
                    </div>
                    <div class="col-xs-12 col-md-6 o_setting_box">
                        <div class="o_setting_left_pane">
                            <field name="load_order_session_option"/>
                        </div>
                        <div class="o_setting_right_pane">
                            <label for="load_order_session_option" string="Opci贸n para cargar sesion"/>
                        </div>
                    </div>
                    <div class="col-xs-12 col-md-6 o_setting_box">
                        <div class="o_setting_right_pane">
                            <label for="session_save_order" string="Sesi贸n para guardar pedidos"/>
                            <div class="content-group mt16">
                                <field name="session_save_order"/>
                            </div>
                        </div>
                    </div>
                    <div class="col-xs-12 col-md-6 o_setting_box">
                        <div class="o_setting_left_pane">
                            <field name="opcion_pedidos_vendedor"/>
                        </div>
                        <div class="o_setting_right_pane">
                            <label for="opcion_pedidos_vendedor" string="Solo cargar pedidos del vendedor"/>
                        </div>
                    </div>
                </div>
            </sheet>
        </field>
    </record>
</odoo>
